cliff/__init__.py
cliff/cliff.py
cliff/config.py
cliff/console.py
cliff/memory.py
cliff/notepad.py
cliff/prompts/notepad.txt
cliff/prompts/system.txt
cliff/resources/ambiguous_model.txt
cliff/resources/config_help.txt
cliff/resources/malformed_response.txt
cliff/resources/man_page.txt
cliff/resources/no_active_models.txt
cliff_cli-0.5.6.dist-info/licenses/LICENSE
cliff_cli-0.5.6.dist-info/METADATA
cliff_cli-0.5.6.dist-info/WHEEL
cliff_cli-0.5.6.dist-info/entry_points.txt
cliff_cli-0.5.6.dist-info/top_level.txt
cliff_cli-0.5.6.dist-info/RECORD
