Metadata-Version: 2.4
Name: cliff-cli
Version: 0.5.6
Summary: Generate Unix commands in the terminal
Author-email: Pierce Kelaita <pierce@kelaita.com>
License-Expression: Apache-2.0
Project-URL: Homepage, https://github.com/pkelaita/cliff
Project-URL: Documentation, https://github.com/pkelaita/cliff/blob/main/README.md
Project-URL: Repository, https://github.com/pkelaita/cliff.git
Project-URL: Issues, https://github.com/pkelaita/cliff/issues
Requires-Python: >=3.10
License-File: LICENSE
Requires-Dist: l2m2==0.0.61
Requires-Dist: pydantic>=2.12.4
Requires-Dist: rich>=14.1.0
Dynamic: license-file
